osmosis_aws_driver/__init__.py
osmosis_aws_driver/computing_plugin.py
osmosis_aws_driver/config_parser.py
osmosis_aws_driver/data_plugin.py
osmosis_aws_driver/log.py
osmosis_aws_driver-0.1.0.dist-info/LICENSE
osmosis_aws_driver-0.1.0.dist-info/METADATA
osmosis_aws_driver-0.1.0.dist-info/WHEEL
osmosis_aws_driver-0.1.0.dist-info/top_level.txt
osmosis_aws_driver-0.1.0.dist-info/RECORD
